xt_training/__init__.py
xt_training/__main__.py
xt_training/metrics.py
xt_training/runner.py
xt_training/utils/__init__.py
xt_training/utils/config_example.py
xt_training/utils/file_utils.py
xt_training/utils/functional.py
xt_training/utils/logging.py
xt_training/utils/sklearn_wrapper.py
xt_training/utils/testing.py
xt_training/utils/training.py
xt_training/utils/nni/config_example.py
xt_training/utils/nni/nni_config_example.yml
xt_training/utils/nni/search_space_example.json
xt_training-2.4.3.dist-info/METADATA
xt_training-2.4.3.dist-info/WHEEL
xt_training-2.4.3.dist-info/top_level.txt
xt_training-2.4.3.dist-info/RECORD
