Metadata-Version: 2.1
Name: xt-training
Version: 2.4.3
Summary: Utilities for training models in pytorch
Home-page: https://github.com/XtractTech/xt-training
Author: Xtract AI
Author-email: info@xtract.ai
License: UNKNOWN
Platform: UNKNOWN
Classifier: Programming Language :: Python :: 3
Classifier: Operating System :: OS Independent
Provides: xt_training
Requires-Dist: numpy
Requires-Dist: pandas
Requires-Dist: torch
Requires-Dist: scikit-learn (>=0.22)
Requires-Dist: plotly
Requires-Dist: pynvml
Requires-Dist: nni
Requires-Dist: gitpython
